indentml/__init__.py
indentml/formatter.py
indentml/indexedlist.py
indentml/parser.py
indentml-0.2.3.post1.dist-info/LICENSE
indentml-0.2.3.post1.dist-info/METADATA
indentml-0.2.3.post1.dist-info/WHEEL
indentml-0.2.3.post1.dist-info/top_level.txt
indentml-0.2.3.post1.dist-info/RECORD
