Metadata-Version: 2.1
Name: indentml
Version: 0.2.3.post1
Summary: indentml is a simple general-purpose indent-based language suitable to describe tree-like structures
Home-page: https://github.com/ischurov/indentml
Author: Ilya V. Schurov
Author-email: ilya@schurov.com
License: MIT
Keywords: indent-based,markup
Platform: UNKNOWN
Classifier: Development Status :: 3 - Alpha
Classifier: Intended Audience :: Developers
Classifier: Topic :: Software Development :: Build Tools
Classifier: Topic :: Software Development :: Documentation
Classifier: License :: OSI Approved :: MIT License
Classifier: Programming Language :: Python :: 3
Classifier: Programming Language :: Python :: 3.6
Classifier: Programming Language :: Python :: 3.7
Classifier: Programming Language :: Python :: 3.8
Classifier: Programming Language :: Python :: 3.9
Classifier: Programming Language :: Python :: 3.10
License-File: LICENSE
Requires-Dist: sortedcontainers
